README.rst
setup.py
python_rest_model.egg-info/PKG-INFO
python_rest_model.egg-info/SOURCES.txt
python_rest_model.egg-info/dependency_links.txt
python_rest_model.egg-info/requires.txt
python_rest_model.egg-info/top_level.txt
rest_model/__init__.py
rest_model/meta_classes.py
rest_model/models.py
rest_model/primitives.py
tests/__init__.py
tests/tests.py