Metadata-Version: 1.1
Name: python-rest-model
Version: 1.0
Summary: A standard way to consume a RESTful service, inspired by Django models
Home-page: https://github.com/mdaif/python-rest-model
Author: Mohamed Daif
Author-email: mohamed@daif.me
License: OSI Approved
Platform: UNKNOWN
Classifier: Intended Audience :: Developers
Classifier: License :: OSI Approved :: Apache Software License
Classifier: Operating System :: OS Independent
Classifier: Programming Language :: Python :: 3.4
